<elo>
<metadata>
  <lom>
    <lifecycle>
      <contribute>
        <role>
          <source>LOMv1.0</source>
          <value>author</value>
        </role>
        <entity>Caspar</entity>
        <date>
          <dateTime>2011-05-10T17:55:24.406+0200</dateTime>
        </date>
      </contribute>
      <version>0</version>
    </lifecycle>
    <technical>
      <customElements>
        <dateCreated>1305042924406</dateCreated>
        <dateLastModified>1305042924406</dateLastModified>
      </customElements>
      <format>scy/pedagogicalplansettings</format>
    </technical>
    <general>
      <identifier>
        <catalog>memory</catalog>
        <entry>roolo://memory/30174/0/pizzaMission.scy</entry>
      </identifier>
      <las>design</las>
      <missionRunning>
        <catalog>memory</catalog>
        <entry>roolo://memory/30169/0/A+Healthy+Pizza+2.7.scymissionspecification</entry>
      </missionRunning>
      <title>
        <string language="en">pizzaMission</string>
      </title>
    </general>
    <relation>
      <kind>
        <source>LOMv1.0</source>
        <value>is_version_of</value>
      </kind>
      <resource>
        <identifier />
      </resource>
    </relation>
  </lom>
</metadata>
<content languageIndependent="true">

</content>
<resources>
</resources>
</elo>