<elo>
<metadata>
  <lom>
    <lifecycle>
      <contribute>
        <role>
          <source>LOMv1.0</source>
          <value>author</value>
        </role>
        <entity>wouter</entity>
        <date>
          <dateTime>2011-06-01T13:46:16.293+0200</dateTime>
        </date>
      </contribute>
      <version>0</version>
    </lifecycle>
    <technical>
      <customElements>
        <dateCreated>1306928776293</dateCreated>
        <dateLastModified>1306928776293</dateLastModified>
      </customElements>
      <format>scy/pedagogicalplansettings</format>
    </technical>
    <general>
      <identifier>
        <catalog>memory</catalog>
        <entry>roolo://memory/50066/0/runForYourLife.scy</entry>
      </identifier>
      <las>information</las>
      <missionRunning>
        <catalog>memory</catalog>
        <entry>roolo://memory/50024/0/RFYL.scymissionspecification</entry>
      </missionRunning>
      <title>
        <string language="en">runForYourLife</string>
      </title>
    </general>
    <relation>
      <kind>
        <source>LOMv1.0</source>
        <value>is_version_of</value>
      </kind>
      <resource>
        <identifier />
      </resource>
    </relation>
  </lom>
</metadata>
<content languageIndependent="true">

</content>
<resources>
</resources>
</elo>