<elo>
<metadata>
  <lom>
    <lifecycle>
      <contribute>
        <role>
          <source>LOMv1.0</source>
          <value>author</value>
        </role>
        <entity>jakob</entity>
        <date>
          <dateTime>2011-06-23T16:34:04.091+0200</dateTime>
        </date>
      </contribute>
      <version>0</version>
    </lifecycle>
    <technical>
      <customElements>
        <dateCreated>1308839644091</dateCreated>
        <dateLastModified>1308839644091</dateLastModified>
      </customElements>
      <format>scy/pedagogicalplansettings</format>
    </technical>
    <general>
      <identifier>
        <catalog>memory</catalog>
        <entry>roolo://memory/737/0/co2MissionRedesignUT.scy</entry>
      </identifier>
      <las />
      <title>
        <string language="en">co2MissionRedesignUT</string>
      </title>
    </general>
    <relation>
      <kind>
        <source>LOMv1.0</source>
        <value>is_version_of</value>
      </kind>
      <resource>
        <identifier />
      </resource>
    </relation>
  </lom>
</metadata>
<content languageIndependent="true">

</content>
<resources>
</resources>
</elo>