<elo>
<metadata>
  <lom>
    <lifecycle>
      <contribute>
        <role>
          <source>LOMv1.0</source>
          <value>author</value>
        </role>
        <entity>rachel</entity>
        <date>
          <dateTime>2010-02-22T13:36:09.329+0100</dateTime>
        </date>
      </contribute>
      <version>6</version>
    </lifecycle>
    <relation>
      <kind>
        <source>LOMv1.0</source>
        <value>containsAssignment</value>
      </kind>
      <resource>
        <identifier>
          <catalog>memory</catalog>
          <entry>roolo://memory/714/0/Welcome_to_SCY-Lab_.url</entry>
        </identifier>
      </resource>
    </relation>
    <technical>
      <customElements>
        <dateCreated>1266836817105</dateCreated>
        <dateLastModified>1266836817106</dateLastModified>
      </customElements>
      <mucId>startPageChat</mucId>
      <format>scy/url</format>
    </technical>
    <general>
      <description>
        <string language="en" />
      </description>
      <identifier>
        <catalog>memory</catalog>
        <entry>roolo://memory/581/0/Challenge.url</entry>
      </identifier>
      <las>startPage</las>
      <structure>information</structure>
      <mission>co2Mission</mission>
      <title>
        <string language="en">Challenge</string>
        <string language="fr">Challenge</string>
      </title>
    </general>
    <educational>
      <learningResourceType>informationAssignment</learningResourceType>
    </educational>
    <annotation>
      <entity>icon</entity>
      <iconType>ard/assignment</iconType>
    </annotation>
  </lom>
  <template>true</template>
</metadata>
<content languageIndependent="true" contentType="xml">
<url>http://www.scy-lab.eu/content/en/mission1Redesign_UT/startPage/A_Challenge.html</url>
</content>
<resources>
</resources>
</elo>